DMBotNetwork/__init__.py
DMBotNetwork/version.py
DMBotNetwork/main/__init__.py
DMBotNetwork/main/client.py
DMBotNetwork/main/server.py
DMBotNetwork/main/utils/__init__.py
DMBotNetwork/main/utils/cl_unit.py
DMBotNetwork/main/utils/decorator.py
DMBotNetwork/main/utils/response_code.py
DMBotNetwork/main/utils/server_db.py
DMBotNetwork/main/utils/states.py
Tests/ServerDB.py
Tests/__init__.py
DMBotNetwork-0.3.2.dist-info/LICENSE.md
DMBotNetwork-0.3.2.dist-info/METADATA
DMBotNetwork-0.3.2.dist-info/WHEEL
DMBotNetwork-0.3.2.dist-info/top_level.txt
DMBotNetwork-0.3.2.dist-info/RECORD
